LICENSE
MANIFEST.in
README.rst
setup.py
google/__init__.py
google/cloud/__init__.py
google/cloud/proto/__init__.py
google/cloud/proto/functions/__init__.py
google/cloud/proto/functions/v1beta2/__init__.py
google/cloud/proto/functions/v1beta2/functions_pb2.py
google/cloud/proto/functions/v1beta2/functions_pb2_grpc.py
google/cloud/proto/functions/v1beta2/operations_pb2.py
google/cloud/proto/functions/v1beta2/operations_pb2_grpc.py
proto_google_cloud_functions_v1beta2.egg-info/PKG-INFO
proto_google_cloud_functions_v1beta2.egg-info/SOURCES.txt
proto_google_cloud_functions_v1beta2.egg-info/dependency_links.txt
proto_google_cloud_functions_v1beta2.egg-info/namespace_packages.txt
proto_google_cloud_functions_v1beta2.egg-info/requires.txt
proto_google_cloud_functions_v1beta2.egg-info/top_level.txt